jcake/__init__.py
jcake/__init__.pyc
jcake/__main__.py
jcake/cli.py
jcake/cli.pyc
jcake/cli_utils.py
jcake/commands.py
jcake/jcake.pyc
jcake/meta.py
jcake/meta.pyc
jcake/options.py
jcake/repository.py
jcake/utils.py
jcake/workspace.py
jcake-0.2.0.dist-info/AUTHORS.rst
jcake-0.2.0.dist-info/METADATA
jcake-0.2.0.dist-info/WHEEL
jcake-0.2.0.dist-info/entry_points.txt
jcake-0.2.0.dist-info/top_level.txt
jcake-0.2.0.dist-info/RECORD
