Metadata-Version: 2.1
Name: jcake
Version: 0.2.0
Summary: Simplify teamates DEVOPS life
Home-page: http://git.kanzhun-inc.com/liulong/jcake.git
Author: ('chuter',)
Author-email: topgun.chuter@gmail.com
License: BSD
Keywords: jcake,java,develop,DEVOPS,lifecycle
Platform: UNKNOWN
Classifier: Development Status :: 2 - Pre-Alpha
Classifier: Intended Audience :: Developers
Classifier: Natural Language :: English
Classifier: Programming Language :: Python :: 3
Classifier: Programming Language :: Python :: 3.4
Classifier: Programming Language :: Python :: 3.5
Classifier: Programming Language :: Python :: 3.6
Classifier: Programming Language :: Python :: 3.7
Requires-Python: >3.4
Requires-Dist: Click (>=6.0)
Requires-Dist: crayons
Requires-Dist: bs4
Provides-Extra: dev
Requires-Dist: check-manifest ; extra == 'dev'
Provides-Extra: test
Requires-Dist: coverage ; extra == 'test'
